chat_completion_md/__init__.py
chat_completion_md/api.py
chat_completion_md/cli.py
chat_completion_md/py.typed
chat_completion_md/types.py
chat_completion_md-0.1.0.dist-info/METADATA
chat_completion_md-0.1.0.dist-info/WHEEL
chat_completion_md-0.1.0.dist-info/entry_points.txt
chat_completion_md-0.1.0.dist-info/licenses/LICENSE
chat_completion_md-0.1.0.dist-info/RECORD
