Metadata-Version: 2.4
Name: chat-completion-md
Version: 0.1.0
Summary: Convert OpenAI chat completion request to markdown and vice versa
Project-URL: Homepage, https://github.com/S1M0N38/chat-completion-md
Project-URL: Issues, https://github.com/S1M0N38/chat-completion-md/issues
Project-URL: Repository, https://github.com/S1M0N38/chat-completion-md
Project-URL: Changelog, https://github.com/S1M0N38/chat-completion-md/blob/main/CHANGELOG.md
Author-email: S1M0N38 <bertolottosimone@gmail.com>
License-File: LICENSE
Classifier: Development Status :: 1 - Planning
Classifier: Framework :: Pytest
Classifier: Intended Audience :: Developers
Classifier: License :: OSI Approved :: MIT License
Classifier: Programming Language :: Python :: 3.11
Classifier: Topic :: Scientific/Engineering :: Artificial Intelligence
Classifier: Topic :: Software Development :: Libraries :: Python Modules
Requires-Python: >=3.11
Requires-Dist: pydantic>=2.10.4
Requires-Dist: pyyaml>=6.0.2
